Metadata-Version: 2.1
Name: Orange3-Text-zh
Version: 1.8.2
Summary: 橙现智能文本挖掘插件.
Home-page: https://chengxianzn.one/
Author: Bioinformatics Laboratory, FRI UL
Author-email: info@biolab.si
License: UNKNOWN
Keywords: orange3-text-zh,data mining,orange3 add-on
Platform: UNKNOWN
License-File: LICENSE
Requires-Dist: anyqt
Requires-Dist: beautifulsoup4
Requires-Dist: biopython
Requires-Dist: conllu
Requires-Dist: docx2txt (>=0.6)
Requires-Dist: gensim (>=4.1.2)
Requires-Dist: httpx
Requires-Dist: jieba
Requires-Dist: lemmagen3
Requires-Dist: lxml
Requires-Dist: nltk (>=3.0.5)
Requires-Dist: numpy
Requires-Dist: odfpy (>=1.3.5)
Requires-Dist: pandas
Requires-Dist: pdfminer3k (>=1.3.1)
Requires-Dist: pyclipper (>=1.2.0)
Requires-Dist: pyqtgraph
Requires-Dist: pyyaml
Requires-Dist: requests
Requires-Dist: scikit-learn
Requires-Dist: scipy
Requires-Dist: serverfiles
Requires-Dist: simhash (>=1.11)
Requires-Dist: six
Requires-Dist: yake
Provides-Extra: doc
Requires-Dist: sphinx ; extra == 'doc'
Requires-Dist: recommonmark ; extra == 'doc'
Requires-Dist: sphinx-rtd-theme ; extra == 'doc'
Requires-Dist: docutils (<0.17) ; extra == 'doc'
Provides-Extra: test
Requires-Dist: coverage ; extra == 'test'
